{
  "id": "dg-light-blue-intense-homme",
  "brandSlug": "dg",
  "brand": "DOLCE & GABBANA",
  "name": "Light Blue Eau Intense Pour Homme",
  "subName": "Eau de Parfum",
  "perfumer": "BLOCKED_SOURCE",
  "gender": "nam",
  "image": "/images/products/dg-light-blue-intense-homme-main.jpg",
  "images": [
    {
      "url": "/images/products/dg-light-blue-intense-homme-main.jpg",
      "source": "amazon",
      "caption": "D&G Light Blue Eau Intense chính hãng",
      "verified": true
    }
  ],
  "description": "(Chờ nguồn xác minh)",
  "productCopy": "## Mùi hương tổng thể\nLight Blue Eau Intense Pour Homme là kiểu aquatic-citrus cực kỳ sáng, mặn và mát, mang đúng tinh thần biển mùa hè Địa Trung Hải. Nó không đi theo hướng ngọt hay quá xanh lá, mà tập trung vào cảm giác nước, gió, nắng và sự sạch rõ rệt. Đây là một chai rất hiệu quả cho người thích mùi nam mùa nóng.\n\nĐiểm mạnh của bản Intense là nó “ra biển” rõ hơn bản thường và bám tốt hơn. Trong khí hậu Việt Nam, đây là kiểu chai rất hợp ban ngày, nắng nóng, đi biển, du lịch hoặc dùng khi cần một mùi hương thoáng và năng lượng cao.\n\n## Diễn biến trên da\nMở đầu citrus và cảm giác aquatic mặn lên rất nhanh, sau đó lớp xạ hương và nền gỗ nhẹ giúp mùi ổn định hơn nhưng vẫn giữ tinh thần biển. Mùi phát triển khá thẳng, dễ hiểu và rất đúng vai trò.\n\nDrydown sạch, mặn nhẹ và bám da kiểu fresh rất dễ chịu. Nó không quá nghệ nhưng cực kỳ thực dụng. Nhược điểm là ai không thích cảm giác aquatic mặn có thể thấy nó hơi “biển” quá mức.\n\n## Độ lưu hương / tỏa hương / hoàn cảnh dùng\nLight Blue Eau Intense Pour Homme có độ lưu hương khá, khoảng 5-7 giờ; tỏa hương vừa. Nó hợp ban ngày, mùa nóng, du lịch, đi biển, hoạt động ngoài trời hoặc làm chai fresh rất đúng chức năng.\n\nỞ Việt Nam, chai này dùng khá khỏe. Ưu điểm là mát, sáng và hợp nắng nóng; nhược điểm là tính chiều sâu và độ khác biệt không lớn.\n\n## Kết luận nhanh: hợp ai, khi nào nên mua\nNếu mày muốn một chai nam aquatic rõ, mặn mát và dùng ngon trong mùa nóng, Light Blue Eau Intense Pour Homme là lựa chọn rất ổn. Nó hợp người thích cảm giác biển thật sự thay vì fresh chung chung.\n\nNên mua khi mày cần một chai summer scent đúng nghĩa. Nếu mày ghét aquatic hoặc thích mùi ấm, nên tránh hướng này.",
  "article": "(Chờ Coder viết bài)",
  "score": {
    "scent": 0,
    "uniqueness": 0,
    "compliments": 0,
    "value": 0,
    "total": 0
  },
  "vibes": [],
  "longevity": 0,
  "sillage": 0,
  "seasons": {
    "spring": 0,
    "summer": 0,
    "fall": 0,
    "winter": 0
  },
  "dayNight": {
    "day": 0,
    "night": 0
  },
  "topNotes": [],
  "middleNotes": [],
  "baseNotes": [],
  "accords": [],
  "tags": [
    "Nam",
    "NEEDS_SOURCE"
  ],
  "sizes": [],
  "basePrice": 0,
  "verdict": "(Chờ nguồn xác minh)",
  "verdictShort": "NEEDS_SOURCE",
  "shopeeOffers": []
}